csp_adapter_symphony/__init__.py
csp_adapter_symphony/adapter.py
csp_adapter_symphony/adapter_config.py
csp_adapter_symphony/mention.py
csp_adapter_symphony/message.py
csp_adapter_symphony/examples/__init__.py
csp_adapter_symphony/examples/hello.py
csp_adapter_symphony/tests/test_adapter.py
csp_adapter_symphony-0.3.1.dist-info/METADATA
csp_adapter_symphony-0.3.1.dist-info/WHEEL
csp_adapter_symphony-0.3.1.dist-info/licenses/LICENSE
csp_adapter_symphony-0.3.1.dist-info/RECORD
